sae_lens/__init__.py
sae_lens/analysis/__init__.py
sae_lens/analysis/compat.py
sae_lens/analysis/hooked_sae_transformer.py
sae_lens/analysis/neuronpedia_integration.py
sae_lens/analysis/sae_transformer_bridge.py
sae_lens/cache_activations_runner.py
sae_lens/config.py
sae_lens/constants.py
sae_lens/evals.py
sae_lens/llm_sae_training_runner.py
sae_lens/load_model.py
sae_lens/loading/__init__.py
sae_lens/loading/pretrained_sae_loaders.py
sae_lens/loading/pretrained_saes_directory.py
sae_lens/pretokenize_runner.py
sae_lens/pretrained_saes.yaml
sae_lens/registry.py
sae_lens/saes/__init__.py
sae_lens/saes/batchtopk_sae.py
sae_lens/saes/gated_sae.py
sae_lens/saes/jumprelu_sae.py
sae_lens/saes/matching_pursuit_sae.py
sae_lens/saes/matryoshka_batchtopk_sae.py
sae_lens/saes/sae.py
sae_lens/saes/standard_sae.py
sae_lens/saes/temporal_sae.py
sae_lens/saes/topk_sae.py
sae_lens/saes/transcoder.py
sae_lens/synthetic/__init__.py
sae_lens/synthetic/activation_generator.py
sae_lens/synthetic/correlation.py
sae_lens/synthetic/evals.py
sae_lens/synthetic/feature_dictionary.py
sae_lens/synthetic/firing_probabilities.py
sae_lens/synthetic/hierarchy.py
sae_lens/synthetic/initialization.py
sae_lens/synthetic/plotting.py
sae_lens/synthetic/stats.py
sae_lens/synthetic/training.py
sae_lens/tokenization_and_batching.py
sae_lens/training/__init__.py
sae_lens/training/activation_scaler.py
sae_lens/training/activations_store.py
sae_lens/training/mixing_buffer.py
sae_lens/training/optim.py
sae_lens/training/sae_trainer.py
sae_lens/training/types.py
sae_lens/training/upload_saes_to_huggingface.py
sae_lens/tutorial/tsea.py
sae_lens/util.py
sae_lens-6.33.0.dist-info/METADATA
sae_lens-6.33.0.dist-info/WHEEL
sae_lens-6.33.0.dist-info/licenses/LICENSE
sae_lens-6.33.0.dist-info/RECORD
