Metadata-Version: 2.4
Name: sae-lens
Version: 6.33.0
Summary: Training and Analyzing Sparse Autoencoders (SAEs)
License: MIT
License-File: LICENSE
Keywords: deep-learning,sparse-autoencoders,mechanistic-interpretability,PyTorch
Author: Joseph Bloom
Requires-Python: >=3.10,<4.0
Classifier: License :: OSI Approved :: MIT License
Classifier: Programming Language :: Python :: 3
Classifier: Programming Language :: Python :: 3.10
Classifier: Programming Language :: Python :: 3.11
Classifier: Programming Language :: Python :: 3.12
Classifier: Programming Language :: Python :: 3.13
Classifier: Programming Language :: Python :: 3.14
Classifier: Topic :: Scientific/Engineering :: Artificial Intelligence
Provides-Extra: mamba
Requires-Dist: babe (>=0.0.7,<0.0.8)
Requires-Dist: datasets (>=3.1.0)
Requires-Dist: mamba-lens (>=0.0.4,<0.0.5) ; extra == "mamba"
Requires-Dist: nltk (>=3.8.1,<4.0.0)
Requires-Dist: plotly (>=5.19.0)
Requires-Dist: plotly-express (>=0.4.1)
Requires-Dist: python-dotenv (>=1.0.1)
Requires-Dist: pyyaml (>=6.0.1,<7.0.0)
Requires-Dist: safetensors (>=0.4.2,<1.0.0)
Requires-Dist: simple-parsing (>=0.1.6,<0.2.0)
Requires-Dist: tenacity (>=9.0.0)
Requires-Dist: transformer-lens (>=2.16.1)
Requires-Dist: transformers (>=4.38.1,<5.0.0)
Requires-Dist: typing-extensions (>=4.10.0,<5.0.0)
Project-URL: Homepage, https://decoderesearch.github.io/SAELens
Project-URL: Repository, https://github.com/decoderesearch/SAELens
